apigatewaydisconnectapi/__init__.py
apigatewaydisconnectapi/models/apigatewaydisconnectapi/2018-11-29/paginators-1.json
apigatewaydisconnectapi/models/apigatewaydisconnectapi/2018-11-29/service-2.json
apigatewaydisconnectapi-0.0.1.dist-info/LICENSE
apigatewaydisconnectapi-0.0.1.dist-info/METADATA
apigatewaydisconnectapi-0.0.1.dist-info/WHEEL
apigatewaydisconnectapi-0.0.1.dist-info/top_level.txt
apigatewaydisconnectapi-0.0.1.dist-info/RECORD
