Metadata-Version: 2.1
Name: apigatewaydisconnectapi
Version: 0.0.1
Summary: Provides a boto3 client class by the same name with a disconnect method for disconnecting websocket clients
Home-page: https://github.com/QuiNovas/apigatewaydisconnectapi
Author: Joseph Wortmann
Author-email: jwortmann@quinovas.com
License: Apache 2.0
Platform: UNKNOWN
Classifier: Development Status :: 4 - Beta
Classifier: Intended Audience :: Developers
Classifier: License :: OSI Approved :: Apache Software License
Classifier: Programming Language :: Python :: 3.7
